{
    "inspection_id": "INS_20260609_133415_5200",
    "timestamp": "2026-06-09T12:34:15Z",
    "image_path": "images/empty/WhatsApp Image 2026-06-08 at 20.55.50 (1).jpeg",
    "zone_id": "Z_TEST_01",
    "overall_status": "warning",
    "issues": [
        {
            "issue_id": "ISS_001",
            "type": "empty_shelf",
            "location": "Prateleira superior, centro",
            "severity": "medium",
            "description": "Falta de stock visível na prateleira superior, com uma fila vazia no centro.",
            "confidence": 0.85,
            "affected_area_pct": 0.15
        },
        {
            "issue_id": "ISS_002",
            "type": "empty_shelf",
            "location": "Prateleira intermédia, lado direito",
            "severity": "low",
            "description": "Um pequeno espaço vazio na prateleira intermédia, lado direito.",
            "confidence": 0.7,
            "affected_area_pct": 0.05
        }
    ],
    "shelf_fill_rate": 0.8,
    "products_detected": [
        "Nestle Pensal",
        "Continente Flocos Chocolate",
        "Continente Flocos Mel",
        "Nestum Mel",
        "Nestum 5 Cereais",
        "Nestum Chocolate",
        "Nestum Pro Cacau",
        "Nestum Pro Morango",
        "Nestum Arroz Zero",
        "Nestum Mel Zero",
        "Nestum Espelta Aveia Zero"
    ],
    "model_reasoning": "PASSO 1: Mapeamento de Categorias. A prateleira contém principalmente cereais de pequeno-almoço de várias marcas (Nestle Pensal, Continente, Nestum) e variedades (Mel, Chocolate, 5 Cereais, Pro, Zero). Os produtos estão organizados por marca e tipo em zonas lógicas em cada prateleira. PASSO 2: Avaliação de Preenchimento. A prateleira superior tem uma falha de stock visível no centro. A prateleira intermédia tem um pequeno espaço vazio no lado direito. As prateleiras inferiores parecem estar bem preenchidas. O shelf_fill_rate estimado é de 80%. PASSO 3: Deteção de Anomalias. Foi detetada uma rutura de stock (empty_shelf) na prateleira superior, no centro, com uma extensão considerável. Foi também detetada uma rutura de stock menor (empty_shelf) na prateleira intermédia, lado direito. Não foram detetados caos, sujidade ou produtos errados. PASSO 4: Classificação de Risco. Foram identificadas duas anomalias de tipo 'empty_shelf', uma de gravidade média e outra de gravidade baixa. A presença de ruturas de stock, mesmo que não graves, justifica um estado de 'warning'."
}