{
    "inspection_id": "INS_20260609_024511_A945",
    "timestamp": "2026-06-09T01:45:11Z",
    "image_path": "images\\normal\\WhatsApp Image 2026-06-08 at 20.55.50 (2).jpeg",
    "zone_id": "Z_TEST_01",
    "overall_status": "ok",
    "issues": [],
    "shelf_fill_rate": 1.0,
    "products_detected": [
        "Sheba",
        "Cesar",
        "Pedigree Rodeo",
        "Pedigree Tasty Minis",
        "Pedigree Dentastix"
    ],
    "model_reasoning": "PASSO 1: Mapeamento de Categorias. A prateleira exibe produtos para animais de companhia, especificamente comida e snacks para cães. Os produtos estão organizados por marca e tipo em zonas lógicas distintas em cada prateleira (ex: latas de comida no topo, sacos de snacks a meio, caixas de snacks na parte inferior). PASSO 2: Avaliação de Preenchimento (shelf_fill_rate). A prateleira parece estar 100% preenchida, sem buracos visíveis ou filas vazias até ao fundo. PASSO 3: Deteção de Anomalias. Não foram detetadas anomalias como caos/sujidade, produtos fora do lugar (violação) ou ruturas de stock evidentes. PASSO 4: Classificação de Risco. Com base na ausência de anomalias, o estado geral é 'ok'."
}